{
"meta":{"test_sets":[],"test_metrics":[],"learn_metrics":[{"best_value":"Min","name":"RMSE"}],"launch_mode":"Train","parameters":"","iteration_count":300,"learn_sets":["learn"],"name":"experiment"},
"iterations":[
{"learn":[3.559715471],"iteration":0,"passed_time":0.004659165257,"remaining_time":1.393090412},
{"learn":[3.542913793],"iteration":1,"passed_time":0.008716330015,"remaining_time":1.298733172},
{"learn":[3.530520356],"iteration":2,"passed_time":0.01270770197,"remaining_time":1.258062495},
{"learn":[3.518951401],"iteration":3,"passed_time":0.0165240631,"remaining_time":1.222780669},
{"learn":[3.509950968],"iteration":4,"passed_time":0.02038099545,"remaining_time":1.202478731},
{"learn":[3.500341966],"iteration":5,"passed_time":0.02437239232,"remaining_time":1.194247223},
{"learn":[3.487841288],"iteration":6,"passed_time":0.02822873836,"remaining_time":1.181574334},
{"learn":[3.475457674],"iteration":7,"passed_time":0.0321460456,"remaining_time":1.173330664},
{"learn":[3.465949424],"iteration":8,"passed_time":0.03594241149,"remaining_time":1.162137972},
{"learn":[3.454324234],"iteration":9,"passed_time":0.04021905039,"remaining_time":1.166352461},
{"learn":[3.446130996],"iteration":10,"passed_time":0.04425852306,"remaining_time":1.162792106},
{"learn":[3.439428794],"iteration":11,"passed_time":0.04813198319,"remaining_time":1.155167597},
{"learn":[3.432441133],"iteration":12,"passed_time":0.05248288224,"remaining_time":1.158660554},
{"learn":[3.423646571],"iteration":13,"passed_time":0.05714194009,"remaining_time":1.167328205},
{"learn":[3.413413436],"iteration":14,"passed_time":0.06151253042,"remaining_time":1.168738078},
{"learn":[3.407239917],"iteration":15,"passed_time":0.06539934211,"remaining_time":1.160838322},
{"learn":[3.398372234],"iteration":16,"passed_time":0.06998627574,"remaining_time":1.165065649},
{"learn":[3.391454532],"iteration":17,"passed_time":0.07395926356,"remaining_time":1.158695129},
{"learn":[3.386687059],"iteration":18,"passed_time":0.07773473014,"remaining_time":1.149655746},
{"learn":[3.38263957],"iteration":19,"passed_time":0.08268700131,"remaining_time":1.157618018},
{"learn":[3.377074532],"iteration":20,"passed_time":0.08705961464,"remaining_time":1.156649166},
{"learn":[3.369191643],"iteration":21,"passed_time":0.09163082769,"remaining_time":1.157880459},
{"learn":[3.360355213],"iteration":22,"passed_time":0.09560963537,"remaining_time":1.151472565},
{"learn":[3.351907924],"iteration":23,"passed_time":0.1004530921,"remaining_time":1.155210559},
{"learn":[3.346151712],"iteration":24,"passed_time":0.1057125997,"remaining_time":1.162838597},
{"learn":[3.339599828],"iteration":25,"passed_time":0.1108028267,"remaining_time":1.167691327},
{"learn":[3.331637216],"iteration":26,"passed_time":0.1155003868,"remaining_time":1.167837244},
{"learn":[3.323757045],"iteration":27,"passed_time":0.1195933343,"remaining_time":1.161763819},
{"learn":[3.318962103],"iteration":28,"passed_time":0.1237308437,"remaining_time":1.156243402},
{"learn":[3.314934845],"iteration":29,"passed_time":0.1276162819,"remaining_time":1.148546537},
{"learn":[3.306655918],"iteration":30,"passed_time":0.1323087784,"remaining_time":1.148098754},
{"learn":[3.299730915],"iteration":31,"passed_time":0.1364406268,"remaining_time":1.14269025},
{"learn":[3.293950531],"iteration":32,"passed_time":0.1407371497,"remaining_time":1.138691484},
{"learn":[3.289078655],"iteration":33,"passed_time":0.1451267686,"remaining_time":1.135403542},
{"learn":[3.286271108],"iteration":34,"passed_time":0.1489109168,"remaining_time":1.12746837},
{"learn":[3.27827633],"iteration":35,"passed_time":0.152841704,"remaining_time":1.120839163},
{"learn":[3.273684814],"iteration":36,"passed_time":0.1567682792,"remaining_time":1.114325876},
{"learn":[3.269016842],"iteration":37,"passed_time":0.1616923258,"remaining_time":1.114826036},
{"learn":[3.263872708],"iteration":38,"passed_time":0.1659390992,"remaining_time":1.11051551},
{"learn":[3.259210235],"iteration":39,"passed_time":0.1703502032,"remaining_time":1.107276321},
{"learn":[3.254193664],"iteration":40,"passed_time":0.1746029636,"remaining_time":1.102979697},
{"learn":[3.249130159],"iteration":41,"passed_time":0.1787829061,"remaining_time":1.098237852},
{"learn":[3.244440218],"iteration":42,"passed_time":0.1830086401,"remaining_time":1.093795826},
{"learn":[3.240142441],"iteration":43,"passed_time":0.1873569221,"remaining_time":1.090076638},
{"learn":[3.235794375],"iteration":44,"passed_time":0.1914148421,"remaining_time":1.084684105},
{"learn":[3.229687024],"iteration":45,"passed_time":0.1956441653,"remaining_time":1.080296043},
{"learn":[3.224484909],"iteration":46,"passed_time":0.1998550723,"remaining_time":1.075815602},
{"learn":[3.219410347],"iteration":47,"passed_time":0.2039499902,"remaining_time":1.070737449},
{"learn":[3.215125409],"iteration":48,"passed_time":0.2081621042,"remaining_time":1.066299758},
{"learn":[3.210599297],"iteration":49,"passed_time":0.212250353,"remaining_time":1.061251765},
{"learn":[3.207500381],"iteration":50,"passed_time":0.2166984694,"remaining_time":1.057998409},
{"learn":[3.206110595],"iteration":51,"passed_time":0.2212113211,"remaining_time":1.055007839},
{"learn":[3.202859844],"iteration":52,"passed_time":0.2253413005,"remaining_time":1.050175495},
{"learn":[3.199023198],"iteration":53,"passed_time":0.2295323518,"remaining_time":1.04564738},
{"learn":[3.19437581],"iteration":54,"passed_time":0.2336930598,"remaining_time":1.040996357},
{"learn":[3.190724393],"iteration":55,"passed_time":0.2379411719,"remaining_time":1.036743677},
{"learn":[3.18648444],"iteration":56,"passed_time":0.2419066202,"remaining_time":1.031286118},
{"learn":[3.183663233],"iteration":57,"passed_time":0.2459723791,"remaining_time":1.026298547},
{"learn":[3.180399526],"iteration":58,"passed_time":0.2502345415,"remaining_time":1.022144483},
{"learn":[3.177123393],"iteration":59,"passed_time":0.2544016102,"remaining_time":1.017606441},
{"learn":[3.17435837],"iteration":60,"passed_time":0.2585227867,"remaining_time":1.012900755},
{"learn":[3.170583842],"iteration":61,"passed_time":0.2627417984,"remaining_time":1.008589484},
{"learn":[3.166836748],"iteration":62,"passed_time":0.2667931096,"remaining_time":1.003650269},
{"learn":[3.162594731],"iteration":63,"passed_time":0.2708596485,"remaining_time":0.998794954},
{"learn":[3.159141569],"iteration":64,"passed_time":0.2749670477,"remaining_time":0.9941116341},
{"learn":[3.155798863],"iteration":65,"passed_time":0.2797388564,"remaining_time":0.9918013999},
{"learn":[3.151642693],"iteration":66,"passed_time":0.2837946775,"remaining_time":0.9869277589},
{"learn":[3.149365298],"iteration":67,"passed_time":0.2879602497,"remaining_time":0.9824526167},
{"learn":[3.145433364],"iteration":68,"passed_time":0.292661114,"remaining_time":0.979778512},
{"learn":[3.141269289],"iteration":69,"passed_time":0.2967604871,"remaining_time":0.9750701718},
{"learn":[3.137516491],"iteration":70,"passed_time":0.301083986,"remaining_time":0.9711018702},
{"learn":[3.133712043],"iteration":71,"passed_time":0.305651581,"remaining_time":0.9678966731},
{"learn":[3.131180395],"iteration":72,"passed_time":0.3097847941,"remaining_time":0.963303401},
{"learn":[3.128469218],"iteration":73,"passed_time":0.3142035854,"remaining_time":0.9595947338},
{"learn":[3.125366473],"iteration":74,"passed_time":0.3182951887,"remaining_time":0.9548855661},
{"learn":[3.122150073],"iteration":75,"passed_time":0.3225145398,"remaining_time":0.95056917},
{"learn":[3.118002351],"iteration":76,"passed_time":0.3268113024,"remaining_time":0.9464794861},
{"learn":[3.115783903],"iteration":77,"passed_time":0.3309107724,"remaining_time":0.9418229675},
{"learn":[3.111990006],"iteration":78,"passed_time":0.3361868797,"remaining_time":0.9404721572},
{"learn":[3.109213767],"iteration":79,"passed_time":0.3404981642,"remaining_time":0.9363699516},
{"learn":[3.106745219],"iteration":80,"passed_time":0.3445700563,"remaining_time":0.9316153375},
{"learn":[3.104256347],"iteration":81,"passed_time":0.3489535492,"remaining_time":0.9277057772},
{"learn":[3.099930201],"iteration":82,"passed_time":0.3531526897,"remaining_time":0.9233028153},
{"learn":[3.097852797],"iteration":83,"passed_time":0.3572016285,"remaining_time":0.9185184733},
{"learn":[3.094921539],"iteration":84,"passed_time":0.3614373629,"remaining_time":0.9142239179},
{"learn":[3.092377611],"iteration":85,"passed_time":0.365627752,"remaining_time":0.9098178946},
{"learn":[3.088086479],"iteration":86,"passed_time":0.3698682499,"remaining_time":0.9055395084},
{"learn":[3.08609887],"iteration":87,"passed_time":0.3738448973,"remaining_time":0.9006263435},
{"learn":[3.083449466],"iteration":88,"passed_time":0.3783191394,"remaining_time":0.8969139147},
{"learn":[3.079730439],"iteration":89,"passed_time":0.3825865474,"remaining_time":0.892701944},
{"learn":[3.076863926],"iteration":90,"passed_time":0.3867749867,"remaining_time":0.8883073869},
{"learn":[3.074206568],"iteration":91,"passed_time":0.3910716927,"remaining_time":0.884162088},
{"learn":[3.071100187],"iteration":92,"passed_time":0.3957327221,"remaining_time":0.880824446},
{"learn":[3.067662124],"iteration":93,"passed_time":0.3998710321,"remaining_time":0.8763131129},
{"learn":[3.064506351],"iteration":94,"passed_time":0.4041905298,"remaining_time":0.872200617},
{"learn":[3.061907402],"iteration":95,"passed_time":0.409196556,"remaining_time":0.8695426816},
{"learn":[3.058292347],"iteration":96,"passed_time":0.4131839207,"remaining_time":0.8647044939},
{"learn":[3.053910676],"iteration":97,"passed_time":0.417291114,"remaining_time":0.8601306635},
{"learn":[3.051597683],"iteration":98,"passed_time":0.4216309004,"remaining_time":0.8560384947},
{"learn":[3.049341627],"iteration":99,"passed_time":0.4255107318,"remaining_time":0.8510214636},
{"learn":[3.046570767],"iteration":100,"passed_time":0.429837279,"remaining_time":0.8469071141},
{"learn":[3.043772801],"iteration":101,"passed_time":0.4339254503,"remaining_time":0.8423258742},
{"learn":[3.042697685],"iteration":102,"passed_time":0.4399171123,"remaining_time":0.8413948654},
{"learn":[3.039962885],"iteration":103,"passed_time":0.4439401342,"remaining_time":0.8366564067},
{"learn":[3.036878324],"iteration":104,"passed_time":0.4477719856,"remaining_time":0.8315765446},
{"learn":[3.033112105],"iteration":105,"passed_time":0.4519569142,"remaining_time":0.8271664278},
{"learn":[3.031313157],"iteration":106,"passed_time":0.4556631111,"remaining_time":0.8218970135},
{"learn":[3.027418825],"iteration":107,"passed_time":0.4595826179,"remaining_time":0.8170357652},
{"learn":[3.025327738],"iteration":108,"passed_time":0.4635459702,"remaining_time":0.8122686267},
{"learn":[3.021616962],"iteration":109,"passed_time":0.4680885939,"remaining_time":0.8085166622},
{"learn":[3.020016569],"iteration":110,"passed_time":0.4720106392,"remaining_time":0.8036937911},
{"learn":[3.018024264],"iteration":111,"passed_time":0.4760093701,"remaining_time":0.7990157284},
{"learn":[3.01491898],"iteration":112,"passed_time":0.480038647,"remaining_time":0.7944002388},
{"learn":[3.013326804],"iteration":113,"passed_time":0.4839884578,"remaining_time":0.7896653785},
{"learn":[3.009007008],"iteration":114,"passed_time":0.4879120743,"remaining_time":0.7849020326},
{"learn":[3.006736328],"iteration":115,"passed_time":0.4918121097,"remaining_time":0.7801157602},
{"learn":[3.003318391],"iteration":116,"passed_time":0.4962093948,"remaining_time":0.7761223867},
{"learn":[2.999196491],"iteration":117,"passed_time":0.5002709876,"remaining_time":0.7716044046},
{"learn":[2.995679395],"iteration":118,"passed_time":0.5041832462,"remaining_time":0.7668669543},
{"learn":[2.991312303],"iteration":119,"passed_time":0.5084510745,"remaining_time":0.7626766117},
{"learn":[2.988878265],"iteration":120,"passed_time":0.5128130086,"remaining_time":0.7586242029},
{"learn":[2.984915436],"iteration":121,"passed_time":0.5168446706,"remaining_time":0.7540848472},
{"learn":[2.980036033],"iteration":122,"passed_time":0.5210513179,"remaining_time":0.749805555},
{"learn":[2.9792343],"iteration":123,"passed_time":0.5250751076,"remaining_time":0.7452678947},
{"learn":[2.975923745],"iteration":124,"passed_time":0.5295455462,"remaining_time":0.7413637646},
{"learn":[2.973190762],"iteration":125,"passed_time":0.5334595764,"remaining_time":0.7366822722},
{"learn":[2.970964956],"iteration":126,"passed_time":0.5376019911,"remaining_time":0.7323239721},
{"learn":[2.968091584],"iteration":127,"passed_time":0.5416868854,"remaining_time":0.7278917522},
{"learn":[2.964557743],"iteration":128,"passed_time":0.5454466137,"remaining_time":0.7230338832},
{"learn":[2.960594824],"iteration":129,"passed_time":0.5494680637,"remaining_time":0.7185351603},
{"learn":[2.957817455],"iteration":130,"passed_time":0.553478869,"remaining_time":0.7140299913},
{"learn":[2.956436358],"iteration":131,"passed_time":0.55727069,"remaining_time":0.7092536055},
{"learn":[2.953171428],"iteration":132,"passed_time":0.5611472151,"remaining_time":0.7045983829},
{"learn":[2.9506471],"iteration":133,"passed_time":0.5651249332,"remaining_time":0.7000801412},
{"learn":[2.9480329],"iteration":134,"passed_time":0.5707112041,"remaining_time":0.6975359162},
{"learn":[2.945159012],"iteration":135,"passed_time":0.5746764299,"remaining_time":0.6929921655},
{"learn":[2.943177957],"iteration":136,"passed_time":0.5786343184,"remaining_time":0.6884481306},
{"learn":[2.940059492],"iteration":137,"passed_time":0.5829955107,"remaining_time":0.6843860343},
{"learn":[2.936549566],"iteration":138,"passed_time":0.5868288353,"remaining_time":0.6797082193},
{"learn":[2.933882243],"iteration":139,"passed_time":0.5905935314,"remaining_time":0.6749640359},
{"learn":[2.931045746],"iteration":140,"passed_time":0.5945334725,"remaining_time":0.6704313626},
{"learn":[2.929137309],"iteration":141,"passed_time":0.5991203895,"remaining_time":0.6666269123},
{"learn":[2.926716091],"iteration":142,"passed_time":0.6031146503,"remaining_time":0.6621608399},
{"learn":[2.924870835],"iteration":143,"passed_time":0.6069587139,"remaining_time":0.6575386067},
{"learn":[2.921490449],"iteration":144,"passed_time":0.6110205292,"remaining_time":0.6531598761},
{"learn":[2.918404394],"iteration":145,"passed_time":0.6149747149,"remaining_time":0.6486719596},
{"learn":[2.915797961],"iteration":146,"passed_time":0.6188950627,"remaining_time":0.6441560857},
{"learn":[2.912739596],"iteration":147,"passed_time":0.6227884544,"remaining_time":0.6396205748},
{"learn":[2.910487556],"iteration":148,"passed_time":0.6274800358,"remaining_time":0.6359025866},
{"learn":[2.908399146],"iteration":149,"passed_time":0.6315010075,"remaining_time":0.6315010075},
{"learn":[2.90545298],"iteration":150,"passed_time":0.6355659742,"remaining_time":0.6271478818},
{"learn":[2.902452433],"iteration":151,"passed_time":0.6394495653,"remaining_time":0.6226219452},
{"learn":[2.901000758],"iteration":152,"passed_time":0.6439048519,"remaining_time":0.6186536813},
{"learn":[2.894820682],"iteration":153,"passed_time":0.6487704719,"remaining_time":0.6150681098},
{"learn":[2.891729794],"iteration":154,"passed_time":0.6526676079,"remaining_time":0.6105600203},
{"learn":[2.889152579],"iteration":155,"passed_time":0.6565976062,"remaining_time":0.606090098},
{"learn":[2.885520127],"iteration":156,"passed_time":0.6606595156,"remaining_time":0.6017472021},
{"learn":[2.883576804],"iteration":157,"passed_time":0.6644224456,"remaining_time":0.59713916},
{"learn":[2.879820541],"iteration":158,"passed_time":0.6682895981,"remaining_time":0.5926341719},
{"learn":[2.876957795],"iteration":159,"passed_time":0.672404209,"remaining_time":0.5883536829},
{"learn":[2.875123499],"iteration":160,"passed_time":0.6761732091,"remaining_time":0.58377687},
{"learn":[2.873488021],"iteration":161,"passed_time":0.6800161997,"remaining_time":0.579273059},
{"learn":[2.870911178],"iteration":162,"passed_time":0.6839213247,"remaining_time":0.5748295796},
{"learn":[2.867726482],"iteration":163,"passed_time":0.6891172928,"remaining_time":0.5714631209},
{"learn":[2.864392901],"iteration":164,"passed_time":0.693344366,"remaining_time":0.567281754},
{"learn":[2.862145047],"iteration":165,"passed_time":0.6970976887,"remaining_time":0.5627174114},
{"learn":[2.859538734],"iteration":166,"passed_time":0.7010711781,"remaining_time":0.5583381239},
{"learn":[2.857053947],"iteration":167,"passed_time":0.7056850629,"remaining_time":0.5544668352},
{"learn":[2.853292594],"iteration":168,"passed_time":0.7096243452,"remaining_time":0.5500638415},
{"learn":[2.850619962],"iteration":169,"passed_time":0.7134583702,"remaining_time":0.5455858125},
{"learn":[2.847988515],"iteration":170,"passed_time":0.7238054484,"remaining_time":0.5460286716},
{"learn":[2.845978736],"iteration":171,"passed_time":0.7319437366,"remaining_time":0.5447023156},
{"learn":[2.843642616],"iteration":172,"passed_time":0.7378825128,"remaining_time":0.5416825383},
{"learn":[2.84141213],"iteration":173,"passed_time":0.7426911484,"remaining_time":0.5378108316},
{"learn":[2.83858306],"iteration":174,"passed_time":0.7483866855,"remaining_time":0.5345619182},
{"learn":[2.835787804],"iteration":175,"passed_time":0.7533069774,"remaining_time":0.5307390068},
{"learn":[2.833497583],"iteration":176,"passed_time":0.7582753766,"remaining_time":0.5269371261},
{"learn":[2.830414623],"iteration":177,"passed_time":0.7634686358,"remaining_time":0.523276256},
{"learn":[2.82775343],"iteration":178,"passed_time":0.7687465474,"remaining_time":0.5196554874},
{"learn":[2.823979849],"iteration":179,"passed_time":0.7748109316,"remaining_time":0.5165406211},
{"learn":[2.822204008],"iteration":180,"passed_time":0.7797177617,"remaining_time":0.5126321196},
{"learn":[2.820927975],"iteration":181,"passed_time":0.7844200643,"remaining_time":0.5085800417},
{"learn":[2.819879789],"iteration":182,"passed_time":0.7889595123,"remaining_time":0.5044167374},
{"learn":[2.818364981],"iteration":183,"passed_time":0.7929136892,"remaining_time":0.4998803693},
{"learn":[2.815431101],"iteration":184,"passed_time":0.7970739969,"remaining_time":0.4954784305},
{"learn":[2.813609278],"iteration":185,"passed_time":0.8010354469,"remaining_time":0.4909572094},
{"learn":[2.808830482],"iteration":186,"passed_time":0.8054905518,"remaining_time":0.48674028},
{"learn":[2.806428343],"iteration":187,"passed_time":0.809540635,"remaining_time":0.4822795272},
{"learn":[2.803722384],"iteration":188,"passed_time":0.8136042928,"remaining_time":0.4778310926},
{"learn":[2.80177016],"iteration":189,"passed_time":0.8177534431,"remaining_time":0.4734362039},
{"learn":[2.798883845],"iteration":190,"passed_time":0.8218316262,"remaining_time":0.4690033888},
{"learn":[2.797576598],"iteration":191,"passed_time":0.8257509254,"remaining_time":0.4644848955},
{"learn":[2.795016814],"iteration":192,"passed_time":0.8297913719,"remaining_time":0.4600397761},
{"learn":[2.793476396],"iteration":193,"passed_time":0.8343520044,"remaining_time":0.4558830539},
{"learn":[2.791233136],"iteration":194,"passed_time":0.8385746585,"remaining_time":0.4515402007},
{"learn":[2.787427954],"iteration":195,"passed_time":0.8427135941,"remaining_time":0.447154152},
{"learn":[2.784665403],"iteration":196,"passed_time":0.8469954289,"remaining_time":0.4428453257},
{"learn":[2.782296518],"iteration":197,"passed_time":0.8510518955,"remaining_time":0.4384206734},
{"learn":[2.780050377],"iteration":198,"passed_time":0.8560876975,"remaining_time":0.4344967711},
{"learn":[2.776904746],"iteration":199,"passed_time":0.8603589151,"remaining_time":0.4301794576},
{"learn":[2.771742965],"iteration":200,"passed_time":0.86478773,"remaining_time":0.4259402252},
{"learn":[2.769108899],"iteration":201,"passed_time":0.8692417288,"remaining_time":0.4217113338},
{"learn":[2.766822313],"iteration":202,"passed_time":0.8731314239,"remaining_time":0.4172105819},
{"learn":[2.765176688],"iteration":203,"passed_time":0.8775591719,"remaining_time":0.4129690221},
{"learn":[2.761504255],"iteration":204,"passed_time":0.8816566886,"remaining_time":0.4085726118},
{"learn":[2.75689507],"iteration":205,"passed_time":0.8856315461,"remaining_time":0.4041231327},
{"learn":[2.754418279],"iteration":206,"passed_time":0.8895423569,"remaining_time":0.3996494647},
{"learn":[2.750493805],"iteration":207,"passed_time":0.8948120936,"remaining_time":0.3957822722},
{"learn":[2.750039781],"iteration":208,"passed_time":0.8987346515,"remaining_time":0.3913150875},
{"learn":[2.747766619],"iteration":209,"passed_time":0.9029476751,"remaining_time":0.386977575},
{"learn":[2.744465103],"iteration":210,"passed_time":0.9073085557,"remaining_time":0.3827036088},
{"learn":[2.741270019],"iteration":211,"passed_time":0.9114521789,"remaining_time":0.3783386403},
{"learn":[2.737863312],"iteration":212,"passed_time":0.9156736577,"remaining_time":0.3740075503},
{"learn":[2.73498652],"iteration":213,"passed_time":0.9197900081,"remaining_time":0.3696352369},
{"learn":[2.730522387],"iteration":214,"passed_time":0.9238906241,"remaining_time":0.3652590839},
{"learn":[2.727579528],"iteration":215,"passed_time":0.9279810028,"remaining_time":0.3608815011},
{"learn":[2.72487692],"iteration":216,"passed_time":0.9320581091,"remaining_time":0.3565014887},
{"learn":[2.722747773],"iteration":217,"passed_time":0.9361290472,"remaining_time":0.3521219352},
{"learn":[2.720031492],"iteration":218,"passed_time":0.9401161147,"remaining_time":0.3477141794},
{"learn":[2.717804406],"iteration":219,"passed_time":0.9441975094,"remaining_time":0.3433445489},
{"learn":[2.713548478],"iteration":220,"passed_time":0.9485103297,"remaining_time":0.3390602536},
{"learn":[2.710379007],"iteration":221,"passed_time":0.9532504658,"remaining_time":0.3349258393},
{"learn":[2.707515101],"iteration":222,"passed_time":0.9572786487,"remaining_time":0.3305401612},
{"learn":[2.704718052],"iteration":223,"passed_time":0.9614140581,"remaining_time":0.3261940554},
{"learn":[2.70150111],"iteration":224,"passed_time":0.9656572799,"remaining_time":0.32188576},
{"learn":[2.699644954],"iteration":225,"passed_time":0.9699011777,"remaining_time":0.3175782617},
{"learn":[2.694435109],"iteration":226,"passed_time":0.9741031268,"remaining_time":0.3132578337},
{"learn":[2.691302351],"iteration":227,"passed_time":0.9784958323,"remaining_time":0.3089986839},
{"learn":[2.686939032],"iteration":228,"passed_time":0.9830650937,"remaining_time":0.3047931077},
{"learn":[2.685501621],"iteration":229,"passed_time":0.9872136161,"remaining_time":0.300456318},
{"learn":[2.684130216],"iteration":230,"passed_time":0.9913700672,"remaining_time":0.2961235266},
{"learn":[2.679779372],"iteration":231,"passed_time":0.9964828212,"remaining_time":0.292072551},
{"learn":[2.679032776],"iteration":232,"passed_time":1.000397984,"remaining_time":0.2876680899},
{"learn":[2.67578191],"iteration":233,"passed_time":1.004327769,"remaining_time":0.2832719349},
{"learn":[2.673644125],"iteration":234,"passed_time":1.008672686,"remaining_time":0.2789945726},
{"learn":[2.671918223],"iteration":235,"passed_time":1.01287245,"remaining_time":0.2746772746},
{"learn":[2.669795053],"iteration":236,"passed_time":1.0169415,"remaining_time":0.2703262216},
{"learn":[2.667173912],"iteration":237,"passed_time":1.021954701,"remaining_time":0.2662234936},
{"learn":[2.666280353],"iteration":238,"passed_time":1.026139094,"remaining_time":0.2619016097},
{"learn":[2.66137707],"iteration":239,"passed_time":1.030172609,"remaining_time":0.2575431522},
{"learn":[2.658439308],"iteration":240,"passed_time":1.034304417,"remaining_time":0.2532114548},
{"learn":[2.656542593],"iteration":241,"passed_time":1.038827451,"remaining_time":0.2489751741},
{"learn":[2.653493253],"iteration":242,"passed_time":1.043017564,"remaining_time":0.244658441},
{"learn":[2.65140908],"iteration":243,"passed_time":1.047622076,"remaining_time":0.2404378536},
{"learn":[2.649158905],"iteration":244,"passed_time":1.052333943,"remaining_time":0.2362382321},
{"learn":[2.645832707],"iteration":245,"passed_time":1.056305881,"remaining_time":0.2318720227},
{"learn":[2.642214697],"iteration":246,"passed_time":1.060130545,"remaining_time":0.2274774043},
{"learn":[2.639700345],"iteration":247,"passed_time":1.063963674,"remaining_time":0.2230891574},
{"learn":[2.637683527],"iteration":248,"passed_time":1.069495426,"remaining_time":0.2190532801},
{"learn":[2.634011661],"iteration":249,"passed_time":1.074278498,"remaining_time":0.2148556996},
{"learn":[2.632354954],"iteration":250,"passed_time":1.078723307,"remaining_time":0.2105874184},
{"learn":[2.630420908],"iteration":251,"passed_time":1.083239937,"remaining_time":0.2063314165},
{"learn":[2.628993327],"iteration":252,"passed_time":1.087429448,"remaining_time":0.2020125853},
{"learn":[2.627398476],"iteration":253,"passed_time":1.091513802,"remaining_time":0.1976757279},
{"learn":[2.625262879],"iteration":254,"passed_time":1.096375079,"remaining_time":0.193477955},
{"learn":[2.622525403],"iteration":255,"passed_time":1.101715095,"remaining_time":0.189357282},
{"learn":[2.62100575],"iteration":256,"passed_time":1.106096092,"remaining_time":0.1850666613},
{"learn":[2.618909394],"iteration":257,"passed_time":1.110431571,"remaining_time":0.1807679301},
{"learn":[2.616236302],"iteration":258,"passed_time":1.114471979,"remaining_time":0.1764222052},
{"learn":[2.614968116],"iteration":259,"passed_time":1.118630421,"remaining_time":0.1720969878},
{"learn":[2.611581323],"iteration":260,"passed_time":1.122821687,"remaining_time":0.1677779532},
{"learn":[2.608553947],"iteration":261,"passed_time":1.128092211,"remaining_time":0.1636164275},
{"learn":[2.606854334],"iteration":262,"passed_time":1.132472897,"remaining_time":0.1593212821},
{"learn":[2.605203988],"iteration":263,"passed_time":1.136422974,"remaining_time":0.1549667692},
{"learn":[2.603114765],"iteration":264,"passed_time":1.141145539,"remaining_time":0.1507173354},
{"learn":[2.600488581],"iteration":265,"passed_time":1.145321656,"remaining_time":0.1463944974},
{"learn":[2.597878034],"iteration":266,"passed_time":1.149543964,"remaining_time":0.1420784675},
{"learn":[2.593213882],"iteration":267,"passed_time":1.159903858,"remaining_time":0.1384959831},
{"learn":[2.591522293],"iteration":268,"passed_time":1.164289273,"remaining_time":0.1341746003},
{"learn":[2.589272584],"iteration":269,"passed_time":1.169003856,"remaining_time":0.1298893174},
{"learn":[2.588177499],"iteration":270,"passed_time":1.173254444,"remaining_time":0.1255512135},
{"learn":[2.587014927],"iteration":271,"passed_time":1.177455326,"remaining_time":0.1212086365},
{"learn":[2.584362694],"iteration":272,"passed_time":1.18169947,"remaining_time":0.1168713762},
{"learn":[2.58329453],"iteration":273,"passed_time":1.185644824,"remaining_time":0.1125064431},
{"learn":[2.580659748],"iteration":274,"passed_time":1.190136252,"remaining_time":0.1081942047},
{"learn":[2.57754661],"iteration":275,"passed_time":1.194393618,"remaining_time":0.1038603146},
{"learn":[2.576139727],"iteration":276,"passed_time":1.198573886,"remaining_time":0.09952057536},
{"learn":[2.57338069],"iteration":277,"passed_time":1.202773018,"remaining_time":0.09518347621},
{"learn":[2.571157142],"iteration":278,"passed_time":1.206917388,"remaining_time":0.09084324427},
{"learn":[2.568574445],"iteration":279,"passed_time":1.211025973,"remaining_time":0.08650185523},
{"learn":[2.566435883],"iteration":280,"passed_time":1.216335568,"remaining_time":0.08224333019},
{"learn":[2.565572792],"iteration":281,"passed_time":1.220236329,"remaining_time":0.07788742523},
{"learn":[2.564853437],"iteration":282,"passed_time":1.224045888,"remaining_time":0.07352925828},
{"learn":[2.562691944],"iteration":283,"passed_time":1.228150328,"remaining_time":0.06919156779},
{"learn":[2.558834777],"iteration":284,"passed_time":1.232257951,"remaining_time":0.06485568161},
{"learn":[2.556572024],"iteration":285,"passed_time":1.236306302,"remaining_time":0.06051849031},
{"learn":[2.554927991],"iteration":286,"passed_time":1.240144855,"remaining_time":0.05617380877},
{"learn":[2.552888008],"iteration":287,"passed_time":1.244454844,"remaining_time":0.05185228518},
{"learn":[2.550964855],"iteration":288,"passed_time":1.248396713,"remaining_time":0.04751682991},
{"learn":[2.549725459],"iteration":289,"passed_time":1.252344895,"remaining_time":0.04318430673},
{"learn":[2.548132656],"iteration":290,"passed_time":1.256800808,"remaining_time":0.03887012808},
{"learn":[2.545438267],"iteration":291,"passed_time":1.260837239,"remaining_time":0.03454348601},
{"learn":[2.544734103],"iteration":292,"passed_time":1.265107066,"remaining_time":0.03022440089},
{"learn":[2.542356361],"iteration":293,"passed_time":1.269866962,"remaining_time":0.02591565229},
{"learn":[2.540033241],"iteration":294,"passed_time":1.274167081,"remaining_time":0.02159605222},
{"learn":[2.538104156],"iteration":295,"passed_time":1.278284853,"remaining_time":0.01727411964},
{"learn":[2.536360818],"iteration":296,"passed_time":1.282457748,"remaining_time":0.01295411867},
{"learn":[2.534595422],"iteration":297,"passed_time":1.286565988,"remaining_time":0.008634671057},
{"learn":[2.531857542],"iteration":298,"passed_time":1.290688255,"remaining_time":0.004316683126},
{"learn":[2.530614996],"iteration":299,"passed_time":1.29481506,"remaining_time":0}
]}